jouvence/__init__.py
jouvence/cli.py
jouvence/console.py
jouvence/document.py
jouvence/html.py
jouvence/parser.py
jouvence/renderer.py
jouvence/version.py
jouvence/resources/html_footer.html
jouvence/resources/html_header.html
jouvence/resources/html_styles.css
jouvence/resources/html_styles.scss
tests/__init__.py
tests/conftest.py
tests/test_action.yaml
tests/test_boneyard.yaml
tests/test_centered.yaml
tests/test_character.yaml
tests/test_dialogue.yaml
tests/test_lyrics.yaml
tests/test_pagebreak.yaml
tests/test_parenthetical.yaml
tests/test_renderer.py
tests/test_sceneheading.yaml
tests/test_scripts.yaml
tests/test_synopsis.yaml
tests/test_titlepage.yaml
tests/test_transitions.yaml
Jouvence-0.4.2.dist-info/LICENSE.rst
Jouvence-0.4.2.dist-info/METADATA
Jouvence-0.4.2.dist-info/WHEEL
Jouvence-0.4.2.dist-info/entry_points.txt
Jouvence-0.4.2.dist-info/top_level.txt
Jouvence-0.4.2.dist-info/RECORD
