Metadata-Version: 2.1
Name: Jouvence
Version: 0.4.2
Summary: A library for parsing and rendering Fountain screenplays.
Home-page: https://bolt80.com/jouvence
Author: Ludovic Chabant
Author-email: ludovic@chabant.com
License: Apache License 2.0
Keywords: fountain screenplay screenwriting screenwriter
Platform: UNKNOWN
Requires-Dist: colorama (>=0.4.1)
Requires-Dist: MarkupSafe (>=1.1.1)
